bamboo/.DS_Store
bamboo/__init__.py
bamboo/codegen/__init__.py
bamboo/codegen/helper.py
bamboo/codegen/opvisit.py
bamboo/codegen/process.py
bamboo/codegen/vardetect.py
bamboo/configuration/__init__.py
bamboo/lang/__init__.py
bamboo/lang/annot.py
bamboo/lang/builtin_func.py
bamboo/lang/dtype.py
bamboo/lang/dtype_ext.py
bamboo/lang/error.py
bamboo/lang/ir/__init__.py
bamboo/lang/ir/build.py
bamboo/lang/ir/expr.py
bamboo/lang/ir/stat.py
bamboo/lang/op.py
bamboo/lang/util.py
bamboo/optim/SW/__init__.py
bamboo/optim/SW/helper.py
bamboo/optim/SW/singlekernel.py
bamboo/optim/SW/swOptMain.py
bamboo/optim/__init__.py
bamboo/optim/proc/OptForTransformer.py
bamboo/optim/proc/ProcASTClassify.py
bamboo/optim/proc/__init__.py
bamboo/optim/proc/conditionanalyzer.py
bamboo/optim/proc/globalanalyse.py
bamboo/optim/proc/graph.py
bamboo/optim/proc/haloanalyzer.py
bamboo/optim/proc/helper.py
bamboo/optim/proc/partition.py
bamboo/optim/proc/workloadbalance.py
bamboo/optim/trans/__init__.py
bamboo/optim/trans/const.py
bamboo/optim/trans/inline.py
bamboo/optim/trans/parallel.py
bamboo/optim/trans/predict.py
bamboo/optim/trans/typecheck.py
bamboo/optim/trans/update.py
bamboolang-1.0.0.dist-info/LICENSE
bamboolang-1.0.0.dist-info/METADATA
bamboolang-1.0.0.dist-info/WHEEL
bamboolang-1.0.0.dist-info/RECORD
