Metadata-Version: 2.1
Name: bamboolang
Version: 1.0.0
Summary: A Domain-Specific Language for PDE Solvers on Structured Grids
License: GPL-3.0-or-later
Author: Sandglass-vic
Author-email: zhouyongxiao19@gmail.com
Requires-Python: ==3.7.10
Classifier: License :: OSI Approved :: GNU General Public License v3 or later (GPLv3+)
Classifier: Programming Language :: Python :: 3
